baka/__init__.py
baka/_compat.py
baka/app.py
baka/config.py
baka/error.py
baka/log.py
baka/renderers.py
baka/resources.py
baka/response.py
baka/routes.py
baka/settings.py
baka/utils.py
baka-0.4.3.dist-info/DESCRIPTION.rst
baka-0.4.3.dist-info/METADATA
baka-0.4.3.dist-info/RECORD
baka-0.4.3.dist-info/WHEEL
baka-0.4.3.dist-info/dependency_links.txt
baka-0.4.3.dist-info/entry_points.txt
baka-0.4.3.dist-info/metadata.json
baka-0.4.3.dist-info/top_level.txt
