Metadata-Version: 2.0
Name: baka
Version: 0.4.3
Summary: Baka framework built top pyramid
Home-page: https://github.com/baka-framework/baka.git
Author: Nanang Suryadi
Author-email: nanang.ask@gmail.com
License: BSD License
Keywords: baka,framework,pyramid
Platform: UNKNOWN
Classifier: Development Status :: 4 - Beta
Classifier: Environment :: Console
Classifier: Environment :: Web Environment
Classifier: Framework :: Pyramid
Classifier: Intended Audience :: Developers
Classifier: License :: OSI Approved :: BSD License
Classifier: Operating System :: OS Independent
Classifier: Programming Language :: Python :: 2.7
Classifier: Programming Language :: Python :: 3.5
Classifier: Programming Language :: Python :: 3.6
Requires-Dist: bson
Requires-Dist: pyramid (>=1.9)
Requires-Dist: setuptools (>=27)
Requires-Dist: trafaret (>=0.12.1.dev0)
Requires-Dist: trafaret-config (>=1.0.1)
Requires-Dist: werkzeug (>=0.12)
Provides-Extra: dev
Requires-Dist: baka; extra == 'dev'
Requires-Dist: coverage; extra == 'dev'
Requires-Dist: mock; extra == 'dev'
Requires-Dist: nose; extra == 'dev'
Requires-Dist: nose-parameterized; extra == 'dev'
Requires-Dist: nosexcover; extra == 'dev'
Requires-Dist: pyramid; extra == 'dev'
Requires-Dist: readme; extra == 'dev'
Requires-Dist: twine; extra == 'dev'
Requires-Dist: webtest; extra == 'dev'
Provides-Extra: docs
Requires-Dist: Sphinx; extra == 'docs'
Provides-Extra: test
Requires-Dist: coverage; extra == 'test'
